diator/__init__.py
diator/mediator.py
diator/py.typed
diator/response.py
diator/container/__init__.py
diator/container/di.py
diator/container/protocol.py
diator/container/rodi.py
diator/dispatcher/__init__.py
diator/dispatcher/default.py
diator/dispatcher/dispatch_result.py
diator/dispatcher/protocol.py
diator/events/__init__.py
diator/events/event.py
diator/events/event_emitter.py
diator/events/event_handler.py
diator/events/map.py
diator/message_brokers/__init__.py
diator/message_brokers/azure.py
diator/message_brokers/protocol.py
diator/message_brokers/redis.py
diator/middlewares/__init__.py
diator/middlewares/base.py
diator/middlewares/logging.py
diator/requests/__init__.py
diator/requests/map.py
diator/requests/request.py
diator/requests/request_handler.py
diator-0.1.2.dist-info/METADATA
diator-0.1.2.dist-info/WHEEL
diator-0.1.2.dist-info/licenses/LICENSE.rst
diator-0.1.2.dist-info/RECORD
